{
  "namespace": ["cfd","js","api","json"],
  "comment": "Create pegout transaction",
  "request": {
    ":class": "CreateRawPegoutRequest",
    ":class:comment": "Request for create pegout transaction",
    "version": 2,
    "version:type": "uint32_t",
    "version:require": "optional",
    "version:comment": "transaction version",
    "locktime": 0,
    "locktime:type": "uint32_t",
    "locktime:require": "optional",
    "locktime:comment": "locktime",
    "txins:require": "optional",
    "txins:comment": "txin list",
    "txins": [
      {
        ":class": "TxInRequest",
        ":class:comment": "The data added to the transaction input.",
        "txid": "",
        "txid:require": "require",
        "txid:comment": "utxo txid",
        "vout": 0,
        "vout:type": "uint32_t",
        "vout:require": "require",
        "vout:comment": "utxo vout",
        "sequence": 4294967295,
        "sequence:type": "uint32_t",
        "sequence:require": "optional",
        "sequence:comment": "sequence number"
      }
    ],
    "txouts:require": "optional",
    "txouts:comment": "txout list",
    "txouts": [
      {
        ":class": "ElementsTxOut",
        ":class:comment": "adding txout data",
        "address": "",
        "address:require": "require",
        "address:comment": "address",
        "amount": 0,
        "amount:require": "require",
        "amount:comment": "satoshi amount",
        "asset": "",
        "asset:require": "require",
        "asset:comment": "asset",
        "directLockingScript": "",
        "directLockingScript:require": "optional",
        "directLockingScript:comment": "locking script",
        "directNonce": "",
        "directNonce:require": "optional",
        "directNonce:comment": "nonce for confidential key",
        "isRemoveNonce": false,
        "isRemoveNonce:require": "optional",
        "isRemoveNonce:comment": "remove nonce flag"
      }
    ],
    "pegout:require": "require",
    "pegout:comment": "pegout txout",
    "pegout": {
      ":class": "ElementsPegoutTxOut",
      ":class:comment": "adding pegout txout data",
      "amount": 0,
      "amount:require": "require",
      "amount:comment": "satoshi amount",
      "asset": "",
      "asset:require": "require",
      "asset:comment": "asset",
      "network": "mainnet",
      "network:require": "require",
      "network:comment": "mainchain network type",
      "network:hint": "mainnet, testnet or regtest",
      "elementsNetwork": "",
      "elementsNetwork:require": "require",
      "elementsNetwork:comment": "elements network type",
      "elementsNetwork:hint": "liquidv1, regtest",
      "mainchainGenesisBlockHash":"",
      "mainchainGenesisBlockHash:require": "require",
      "mainchainGenesisBlockHash:comment": "mainchain genesis block hash",
      "btcAddress": "",
      "btcAddress:require": "optional",
      "btcAddress:comment": "bitcoin address",
      "onlinePubkey":"",
      "onlinePubkey:require": "require",
      "onlinePubkey:comment": "online pubkey.",
      "masterOnlineKey":"",
      "masterOnlineKey:require": "require",
      "masterOnlineKey:comment": "master online privkey.",
      "bitcoinDescriptor":"",
      "bitcoinDescriptor:require": "require",
      "bitcoinDescriptor:comment": "output descriptor for pegout",
      "bip32Counter":0,
      "bip32Counter:require": "require",
      "bip32Counter:comment": "descriptor's bip32 counter.",
      "bip32Counter:type": "uint32_t",
      "whitelist":"",
      "whitelist:require": "require",
      "whitelist:comment": "whitelist"
    },
    "fee:require": "optional",
    "fee:comment": "fee data",
    "fee": {
      ":class": "ElementsTxOutFee",
      ":class:comment": "Transaction fee data.",
      "amount": 0,
      "amount:require": "require",
      "amount:comment": "satoshi amount",
      "asset": "",
      "asset:require": "require",
      "asset:comment": "asset"
    }
  },
  "response": {
    ":class": "CreateRawPegoutResponse",
    ":class:comment": "Response of create pegout transaction.",
    "hex": "",
    "hex:require": "require",
    "hex:comment": "transaction hex",
    "btcAddress": "",
    "btcAddress:require": "optional",
    "btcAddresses:comment": "pegout address."
  }
}