{
  "namespace": ["cfd","js","api","json"],
  "functionName": "GetTapScriptTreeInfo",
  "comment": "Get TapScript tree info.",
  "request": {
    ":class": "GetTapScriptTreeInfoRequest",
    ":class:comment": "Request for get tapscript info.",
    "network": "mainnet",
    "network:require": "optional",
    "network:comment": "network type",
    "network:hint": "bitcoin:'mainnet, testnet, regtest'. elements:'liquidv1, regtest'",
    "isElements": false,
    "isElements:require": "optional",
    "isElements:comment": "elements transaction flag.",
    "internalPubkey": "",
    "internalPubkey:require": "optional",
    "internalPubkey:comment": "internal schnorr pubkey.",
    "internalPrivkey": "",
    "internalPrivkey:require": "optional",
    "internalPrivkey:comment": "internal privkey. Specify only when it is necessary to calculate.",
    "tree:require": "require",
    "tree:comment": "tapscript tree. Set tapleaf first, then add branches after that. If you want to connect different trees, after creating that tree, set the topBranchHash of the tree to the branchHash in this tree. (Otherwise, use the tree string.)",
    "tree": [{
      ":class": "TapBranchData",
      ":class:comment": "TapBranch data.",
      "tapscript": "",
      "tapscript:require": "optional",
      "tapscript:comment": "tapscript hex.",
      "branchHash": "",
      "branchHash:require": "optional",
      "branchHash:comment": "tapbranch hash only. (to hide the tapscript)",
      "treeString": "",
      "treeString:require": "optional",
      "treeString:comment": "tree serialize string. (cfd format)"
    }]
  },
  "response": {
    ":class": "TapScriptInfo",
    ":class:comment": "TapScript information",
    "tapLeafHash": "",
    "tapLeafHash:require": "optional",
    "tapLeafHash:comment": "tapleaf hash",
    "topBranchHash": "",
    "topBranchHash:require": "require",
    "topBranchHash:comment": "branch hash on the top.",
    "tweakedPubkey": "",
    "tweakedPubkey:require": "optional",
    "tweakedPubkey:comment": "tweaked schnorr pubkey with internal pubkey.",
    "tweakedPrivkey": "",
    "tweakedPrivkey:require": "optional",
    "tweakedPrivkey:comment": "tweaked privkey with internal privkey.",
    "address": "",
    "address:require": "optional",
    "address:comment": "address",
    "lockingScript": "",
    "lockingScript:require": "optional",
    "lockingScript:comment": "locking script",
    "controlBlock": "",
    "controlBlock:require": "optional",
    "controlBlock:comment": "control block",
    "tapscript": "",
    "tapscript:require": "optional",
    "tapscript:comment": "tapscript",
    "nodes": [""],
    "nodes:require": "optional",
    "nodes:comment": "tapbranch list in this tree.",
    "treeString": "",
    "treeString:require": "require",
    "treeString:comment": "tree serialize string. (cfd format)"
  }
}